spl_core/__init__.py
spl_core/__run.py
spl_core/common/__init__.py
spl_core/common/path.py
spl_core/common.cmake
spl_core/conan.cmake
spl_core/config/KConfig
spl_core/gcov_maid/__init__.py
spl_core/gcov_maid/gcov_maid.py
spl_core/kconfig/__init__.py
spl_core/kconfig/kconfig.py
spl_core/kconfig.cmake
spl_core/kickstart/__init__.py
spl_core/kickstart/create.py
spl_core/kickstart/templates/application/.vscode/cmake-variants.json
spl_core/kickstart/templates/application/KConfig
spl_core/kickstart/templates/application/src/greeter/CMakeLists.txt
spl_core/kickstart/templates/application/src/greeter/doc/_images/screenshot.png
spl_core/kickstart/templates/application/src/greeter/doc/index.md
spl_core/kickstart/templates/application/src/greeter/src/greeter.c
spl_core/kickstart/templates/application/src/greeter/src/greeter.h
spl_core/kickstart/templates/application/src/greeter/test/test_greeter.cc
spl_core/kickstart/templates/application/src/main/CMakeLists.txt
spl_core/kickstart/templates/application/src/main/doc/index.md
spl_core/kickstart/templates/application/src/main/src/main.c
spl_core/kickstart/templates/application/test/EnglishVariant/test__EnglishVariant.py
spl_core/kickstart/templates/application/test/German/test__GermanVariant.py
spl_core/kickstart/templates/application/variants/EnglishVariant/config.cmake
spl_core/kickstart/templates/application/variants/EnglishVariant/parts.cmake
spl_core/kickstart/templates/application/variants/GermanVariant/config.cmake
spl_core/kickstart/templates/application/variants/GermanVariant/config.txt
spl_core/kickstart/templates/application/variants/GermanVariant/parts.cmake
spl_core/kickstart/templates/project/.gitignore
spl_core/kickstart/templates/project/.vscode/cmake-kits.json
spl_core/kickstart/templates/project/.vscode/extensions.json
spl_core/kickstart/templates/project/.vscode/launch.json
spl_core/kickstart/templates/project/.vscode/settings.json
spl_core/kickstart/templates/project/.vscode/tasks.json
spl_core-7.14.0.dist-info/METADATA
spl_core-7.14.0.dist-info/WHEEL
spl_core-7.14.0.dist-info/entry_points.txt
spl_core-7.14.0.dist-info/licenses/LICENSE
spl_core-7.14.0.dist-info/RECORD
