Metadata-Version: 2.4
Name: spl-core
Version: 7.14.0
Summary: Software Product Line Support for CMake
License: MIT
License-File: LICENSE
Author: Avengineers
Author-email: karsten.guenther@kamg.de
Requires-Python: >=3.10,<3.12
Classifier: Development Status :: 2 - Pre-Alpha
Classifier: Intended Audience :: Developers
Classifier: License :: OSI Approved :: MIT License
Classifier: Natural Language :: English
Classifier: Operating System :: OS Independent
Classifier: Programming Language :: Python :: 3
Classifier: Programming Language :: Python :: 3.10
Classifier: Programming Language :: Python :: 3.11
Classifier: Topic :: Software Development :: Libraries
Requires-Dist: cookiecutter (==2.6.0)
Requires-Dist: doxysphinx (>=3.3,<4.0)
Requires-Dist: gcovr (>=8.3,<9.0)
Requires-Dist: hammocking (>=0.8,<0.10)
Requires-Dist: kconfiglib (>=14.1,<15.0)
Requires-Dist: mlx-traceability (>=10,<12)
Requires-Dist: myst-parser (>=0.16)
Requires-Dist: py-app-dev (>=2.1,<3.0)
Requires-Dist: py7zr (>=1.0.0,<2.0.0)
Requires-Dist: pypeline-runner (>=1,<=2)
Requires-Dist: pypeline-semantic-release (>=0.4.1,<=0.5.0)
Requires-Dist: sphinx (>=7.3,<8.0)
Requires-Dist: sphinx-book-theme (>=1.1,<2.0)
Requires-Dist: sphinx-copybutton (>=0.5,<0.6)
Requires-Dist: sphinx-design (>=0.5,<0.7)
Requires-Dist: sphinx-needs (>=2.0,<3.0)
Requires-Dist: sphinx-new-tab-link (>=0.4,<0.9)
Requires-Dist: sphinx-rtd-size (>=0.2,<0.3)
Requires-Dist: sphinx-rtd-theme (>=2.0,<3.0)
Requires-Dist: sphinx-test-reports (>=1.0,<2.0)
Requires-Dist: sphinxcontrib-datatemplates (>=0.11,<0.12)
Requires-Dist: sphinxcontrib-mermaid (>=0.9,<0.10)
Requires-Dist: sphinxcontrib-plantuml (>=0.29,<0.31)
Requires-Dist: typer (>=0,<1)
Project-URL: Bug Tracker, https://github.com/avengineers/spl-core/issues
Project-URL: Changelog, https://github.com/avengineers/spl-core/blob/develop/CHANGELOG.md
Project-URL: Documentation, https://spl-core.readthedocs.io
Project-URL: Repository, https://github.com/avengineers/spl-core
